gsheet_manager/__init__.py
gsheet_manager/gsheet_manager.py
gsheet_manager-0.4.0.dist-info/LICENSE
gsheet_manager-0.4.0.dist-info/METADATA
gsheet_manager-0.4.0.dist-info/WHEEL
gsheet_manager-0.4.0.dist-info/top_level.txt
gsheet_manager-0.4.0.dist-info/RECORD
