Metadata-Version: 2.1
Name: gsheet-manager
Version: 0.4.0
Summary: A Google Sheets manager for Python
Home-page: https://github.com/coallaoh/gsheet-manager
Author: Seong Joon Oh
Author-email: coallaoh@gmail.com
Classifier: Programming Language :: Python :: 3
Classifier: License :: OSI Approved :: MIT License
Classifier: Operating System :: OS Independent
Requires-Python: >=3.6
License-File: LICENSE
Requires-Dist: gspread >=5.0.0
